[{"annotations":{"DMS":{"lat":"7° 22' 39.15732'' N","lng":"3° 53' 51.38016'' E"},"MGRS":"31NEJ9906315584","Maidenhead":"JJ17wj70ro","Mercator":{"x":433879.468,"y":818060.371},"OSM":{"edit_url":"https://www.openstreetmap.org/edit?way=230737992#map=17/7.37754/3.89761","note_url":"https://www.openstreetmap.org/note/new#map=17/7.37754/3.89761&layers=N","url":"https://www.openstreetmap.org/?mlat=7.37754&mlon=3.89761#map=17/7.37754/3.89761"},"UN_M49":{"regions":{"AFRICA":"002","NG":"566","SUB-SAHARAN_AFRICA":"202","WESTERN_AFRICA":"011","WORLD":"001"},"statistical_groupings":["LEDC"]},"callingcode":234,"currency":{"alternate_symbols":[],"decimal_mark":".","html_entity":"&#x20A6;","iso_code":"NGN","iso_numeric":"566","name":"Nigerian Naira","smallest_denomination":50,"subunit":"Kobo","subunit_to_unit":100,"symbol":"₦","symbol_first":1,"thousands_separator":","},"flag":"🇳🇬","geohash":"s16cbxn1kcc65dcsw4eu","qibla":64.08,"roadinfo":{"drive_on":"right","road":"A1","road_reference":"A1","road_type":"trunk","speed_in":"km/h"},"sun":{"rise":{"apparent":1694237820,"astronomical":1694233620,"civil":1694236560,"nautical":1694235120},"set":{"apparent":1694281620,"astronomical":1694285760,"civil":1694282880,"nautical":1694284320}},"timezone":{"name":"Africa/Lagos","now_in_dst":0,"offset_sec":3600,"offset_string":"+0100","short_name":"WAT"},"what3words":{"words":"poster.blinking.excuse"}},"bounds":{"northeast":{"lat":7.3793183,"lng":3.898784},"southwest":{"lat":7.3761859,"lng":3.8963008}},"components":{"ISO_3166-1_alpha-2":"NG","ISO_3166-1_alpha-3":"NGA","_category":"road","_type":"road","city":"Ibadan","continent":"Africa","country":"Nigeria","country_code":"ng","county":"Ibadan South West","road":"A1","road_reference":"A1","road_type":"trunk"},"confidence":9,"formatted":"A1, Ibadan, Nigeria","geometry":{"lat":7.3775437,"lng":3.8976056}}]